setup.py
entity_extraction/__init__.py
entity_extraction/flask_api_main.py
entity_extraction.egg-info/PKG-INFO
entity_extraction.egg-info/SOURCES.txt
entity_extraction.egg-info/dependency_links.txt
entity_extraction.egg-info/top_level.txt