Metadata-Version: 2.1
Name: entity-extraction
Version: 0.1
Summary: My Python Package
Home-page: UNKNOWN
License: UNKNOWN
Platform: UNKNOWN
